flet_secure_storage/__init__.py
flet_secure_storage/secure_storage.py
flet_secure_storage/types.py
flet_secure_storage-0.80.5.dist-info/licenses/LICENSE
flutter/flet_secure_storage/pubspec.lock
flutter/flet_secure_storage/pubspec.yaml
flutter/flet_secure_storage/lib/flet_secure_storage.dart
flutter/flet_secure_storage/lib/src/extension.dart
flutter/flet_secure_storage/lib/src/secure_storage.dart
flutter/flet_secure_storage/lib/src/utils/secure_storage.dart
flet_secure_storage-0.80.5.dist-info/METADATA
flet_secure_storage-0.80.5.dist-info/WHEEL
flet_secure_storage-0.80.5.dist-info/top_level.txt
flet_secure_storage-0.80.5.dist-info/RECORD
