Metadata-Version: 2.4
Name: flet-secure-storage
Version: 0.80.5
Summary: Secure Storage control for Flet
Author-email: "Appveyor Systems Inc." <hello@flet.dev>
Project-URL: Homepage, https://flet.dev
Project-URL: Documentation, https://docs.flet.dev/secure-storage
Project-URL: Repository, https://github.com/flet-dev/flet/tree/main/sdk/python/packages/flet-secure-storage
Project-URL: Issues, https://github.com/flet-dev/flet/issues
Requires-Python: >=3.10
License-File: LICENSE
Requires-Dist: flet==0.80.5
Dynamic: license-file
